stac_auth_proxy/__init__.py
stac_auth_proxy/__main__.py
stac_auth_proxy/app.py
stac_auth_proxy/config.py
stac_auth_proxy/lambda.py
stac_auth_proxy/lifespan.py
stac_auth_proxy/filters/__init__.py
stac_auth_proxy/filters/opa.py
stac_auth_proxy/filters/template.py
stac_auth_proxy/handlers/__init__.py
stac_auth_proxy/handlers/healthz.py
stac_auth_proxy/handlers/reverse_proxy.py
stac_auth_proxy/handlers/swagger_ui.py
stac_auth_proxy/middleware/AddProcessTimeHeaderMiddleware.py
stac_auth_proxy/middleware/AuthenticationExtensionMiddleware.py
stac_auth_proxy/middleware/Cql2ApplyFilterBodyMiddleware.py
stac_auth_proxy/middleware/Cql2ApplyFilterQueryStringMiddleware.py
stac_auth_proxy/middleware/Cql2BuildFilterMiddleware.py
stac_auth_proxy/middleware/Cql2RewriteLinksFilterMiddleware.py
stac_auth_proxy/middleware/Cql2ValidateResponseBodyMiddleware.py
stac_auth_proxy/middleware/EnforceAuthMiddleware.py
stac_auth_proxy/middleware/ProcessLinksMiddleware.py
stac_auth_proxy/middleware/RemoveRootPathMiddleware.py
stac_auth_proxy/middleware/UpdateOpenApiMiddleware.py
stac_auth_proxy/middleware/__init__.py
stac_auth_proxy/utils/__init__.py
stac_auth_proxy/utils/cache.py
stac_auth_proxy/utils/filters.py
stac_auth_proxy/utils/middleware.py
stac_auth_proxy/utils/requests.py
stac_auth_proxy/utils/stac.py
stac_auth_proxy-0.11.0.dist-info/METADATA
stac_auth_proxy-0.11.0.dist-info/WHEEL
stac_auth_proxy-0.11.0.dist-info/licenses/LICENSE
stac_auth_proxy-0.11.0.dist-info/RECORD
