Metadata-Version: 2.4
Name: stac-auth-proxy
Version: 0.11.0
Summary: STAC authentication proxy with FastAPI
Author-email: Anthony Lukach <anthonylukach@gmail.com>
License: MIT License
License-File: LICENSE
Keywords: Authentication,FastAPI,Proxy,STAC
Classifier: License :: OSI Approved :: MIT License
Classifier: Programming Language :: Python :: 3
Classifier: Programming Language :: Python :: 3.8
Requires-Python: >=3.10
Requires-Dist: boto3>=1.37.16
Requires-Dist: brotli>=1.1.0
Requires-Dist: cql2>=0.4.2
Requires-Dist: cryptography>=44.0.1
Requires-Dist: fastapi>=0.115.5
Requires-Dist: httpx[http2]>=0.28.0
Requires-Dist: jinja2>=3.1.4
Requires-Dist: pydantic-settings>=2.6.1
Requires-Dist: pyjwt>=2.10.1
Requires-Dist: starlette-cramjam>=0.4.0
Requires-Dist: uvicorn>=0.32.1
Provides-Extra: docs
Requires-Dist: griffe-fieldz>=0.3.0; extra == 'docs'
Requires-Dist: griffe-inherited-docstrings>=1.1.1; extra == 'docs'
Requires-Dist: markdown-gfm-admonition>=0.1.1; extra == 'docs'
Requires-Dist: mkdocs-api-autonav>=0.3.0; extra == 'docs'
Requires-Dist: mkdocs-material[imaging]>=9.6.16; extra == 'docs'
Requires-Dist: mkdocs>=1.6.1; extra == 'docs'
Requires-Dist: mkdocstrings[python]>=0.30.0; extra == 'docs'
Provides-Extra: lambda
Requires-Dist: mangum>=0.19.0; extra == 'lambda'
